32-Bit ALU/src/alu.v
module alu (
    input [31:0] a, b,
    input [2:0] op,
    output reg [31:0] out,
    output zero
);

    localparam alu_add  = 3'b000;
    localparam alu_sub  = 3'b001;
    localparam alu_and  = 3'b010;
    localparam alu_or = 3'b011;
    localparam alu_xor  = 3'b100;
    localparam alu_slt  = 3'b101;
    localparam alu_sll  = 3'b110;
    localparam alu_srl  = 3'b111;

    always @(*) begin
        case(op)
            alu_add: out = a + b;
            alu_sub: out = a - b;
            alu_and: out = a & b;
            alu_or: out = a | b;
            alu_xor: out = a ^ b;
            alu_slt: out = $signed(a) < $signed(b) ? 32'b1 : 32'b0;
            alu_sll: out = a << b[5:0];
            alu_srl: out = a >> b[5:0];
            default: out = 32'b0;
        endcase
    end

    assign zero = (32'b0 == out);

endmodule

32-Bit ALU/sim/alu_tb.v
module alu_tb;
    reg [31:0] a, b;
    reg [2:0] op;
    wire [31:0] out;    
    wire zero;   

    alu uut (
        .a(a),
        .b(b),
        .op(op),
        .out(out),
        .zero(zero)
    );

    initial begin
        $dumpfile("wave.vcd");  // Name of VCD file
        $dumpvars(0, alu_tb);  // Dump all signals in this module

        a = 10; b = 5; op = 3'b000; #10;
        a = 12; b = 12; op = 3'b001; #10;
        a = 32'hF00F; b = 32'h0FF0; op = 3'b010; #10;
        a = 32'h0FF0; b = 32'hF00F; op = 3'b011; #10;
        a = 32'hAAAA; b = 32'h5555; op = 3'b100; #10;
        a = -5; b = 3; op = 3'b101; #10;
        a = 1; b = 4; op = 3'b110; #10;
        a = 8; b = 2; op = 3'b111; #10;

        $finish;
    end

endmodule

32-Bit ALU/wave.vcd
$date
	Sun Sep 28 20:24:44 2025
$end
$version
	Icarus Verilog
$end
$timescale
	1s
$end
$scope module alu_tb $end
$var wire 1 ! zero $end
$var wire 32 " out [31:0] $end
$var reg 32 # a [31:0] $end
$var reg 32 $ b [31:0] $end
$var reg 3 % op [2:0] $end
$scope module uut $end
$var wire 32 & a [31:0] $end
$var wire 32 ' b [31:0] $end
$var wire 3 ( op [2:0] $end
$var wire 1 ! zero $end
$var parameter 3 ) alu_add $end
$var parameter 3 * alu_and $end
$var parameter 3 + alu_or $end
$var parameter 3 , alu_sll $end
$var parameter 3 - alu_slt $end
$var parameter 3 . alu_srl $end
$var parameter 3 / alu_sub $end
$var parameter 3 0 alu_xor $end
$var reg 32 1 out [31:0] $end
$upscope $end
$upscope $end
$enddefinitions $end
$comment Show the parameter values. $end
$dumpall
b100 0
b1 /
b111 .
b101 -
b110 ,
b11 +
b10 *
b0 )
$end
#0
$dumpvars
b1111 1
b0 (
b101 '
b1010 &
b0 %
b101 $
b1010 #
b1111 "
0!
$end
#10
1!
b0 "
b0 1
b1 %
b1 (
b1100 $
b1100 '
b1100 #
b1100 &
#20
b10 %
b10 (
b111111110000 $
b111111110000 '
b1111000000001111 #
b1111000000001111 &
#30
0!
b1111111111111111 "
b1111111111111111 1
b11 %
b11 (
b1111000000001111 $
b1111000000001111 '
b111111110000 #
b111111110000 &
#40
b100 %
b100 (
b101010101010101 $
b101010101010101 '
b1010101010101010 #
b1010101010101010 &
#50
b1 "
b1 1
b101 %
b101 (
b11 $
b11 '
b11111111111111111111111111111011 #
b11111111111111111111111111111011 &
#60
b10000 "
b10000 1
b110 %
b110 (
b100 $
b100 '
b1 #
b1 &
#70
b10 "
b10 1
b111 %
b111 (
b10 $
b10 '
b1000 #
b1000 &
