128x32 RAM/src/ram.v
module ram #(
    parameter BITS_PER_WORD = 32,
    parameter ADDRESS_BITS = 7
)(
    input clk,
    input write_RAM,
    input reset,
    input [ADDRESS_BITS-1:0] address,
    input [BITS_PER_WORD-1:0] in,
    output reg [BITS_PER_WORD-1:0] out
);
    reg [BITS_PER_WORD-1:0] memory [(1<<ADDRESS_BITS)-1:0];
    integer i;

    always @(posedge clk) begin
        if (reset) begin
            for (i = 0; i < (1<<ADDRESS_BITS); i++)
                memory[i] <= 0;
            out <= 0;
        end
        else begin
            if (write_RAM) begin
                memory[address] <= in;
            end
            out <= memory[address];
        end
    end

endmodule

128x32 RAM/sim/ram_tb.v
module ram_tb #(
    parameter BITS_PER_WORD = 32,
    parameter ADDRESS_BITS = 7
);
    reg clk;
    reg write_RAM;
    reg reset;
    reg [ADDRESS_BITS-1:0] address;
    reg [BITS_PER_WORD-1:0] in;
    wire [BITS_PER_WORD-1:0] out;

    ram uut (
        .clk(clk),
        .write_RAM(write_RAM),
        .reset(reset),
        .address(address),
        .in(in),
        .out(out)
    );

    initial clk = 0;
    always #5 clk = ~clk;

    initial begin
        $dumpfile("wave.vcd");  // Name of VCD file
        $dumpvars(0, ram_tb);  // Dump all signals in this module

        write_RAM = 0; address = 0; in = 0; reset = 0;
        #10;
        write_RAM = 1; address = 4; in = 32'd44;
        #10;
        write_RAM = 0; address = 4; in = 0;
        #10; 
        write_RAM = 1; address = 2; in = 32'd7;
        #10;
        write_RAM = 0; address = 2; in = 0;
        #10;
        reset = 1;
        #10;
        reset = 0; address = 2; in = 0;
        #10;

        $finish;
    end


endmodule

128x32 RAM/wave.vcd
$date
	Tue Sep 30 15:55:26 2025
$end
$version
	Icarus Verilog
$end
$timescale
	1s
$end
$scope module ram_tb $end
$var wire 32 ! out [31:0] $end
$var parameter 32 " ADDRESS_BITS $end
$var parameter 32 # BITS_PER_WORD $end
$var reg 7 $ address [6:0] $end
$var reg 1 % clk $end
$var reg 32 & in [31:0] $end
$var reg 1 ' reset $end
$var reg 1 ( write_RAM $end
$scope module uut $end
$var wire 7 ) address [6:0] $end
$var wire 1 % clk $end
$var wire 32 * in [31:0] $end
$var wire 1 ' reset $end
$var wire 1 ( write_RAM $end
$var parameter 32 + ADDRESS_BITS $end
$var parameter 32 , BITS_PER_WORD $end
$var reg 32 - out [31:0] $end
$var integer 32 . i [31:0] $end
$upscope $end
$upscope $end
$enddefinitions $end
$comment Show the parameter values. $end
$dumpall
b100000 ,
b111 +
b100000 #
b111 "
$end
#0
$dumpvars
bx .
bx -
b0 *
b0 )
0(
0'
b0 &
0%
b0 $
bx !
$end
#5
1%
#10
0%
b101100 &
b101100 *
b100 $
b100 )
1(
#15
1%
#20
0%
b0 &
b0 *
0(
#25
b101100 !
b101100 -
1%
#30
0%
b111 &
b111 *
b10 $
b10 )
1(
#35
bx !
bx -
1%
#40
0%
b0 &
b0 *
0(
#45
b111 !
b111 -
1%
#50
0%
1'
#55
b0 !
b0 -
b10000000 .
1%
#60
0%
0'
